peneira/__init__.py
peneira/cli.py
peneira/exporters.py
peneira/sources/__init__.py
peneira/sources/open_alex.py
peneira/sources/semantic_scholar.py
peneira-0.2.1.dist-info/LICENSE
peneira-0.2.1.dist-info/METADATA
peneira-0.2.1.dist-info/WHEEL
peneira-0.2.1.dist-info/entry_points.txt
peneira-0.2.1.dist-info/RECORD
