Metadata-Version: 2.1
Name: peneira
Version: 0.2.1
Summary: Peneira: academic papers from many sources in one command
License: MIT
Author: Ana Paula Gomes
Author-email: apgomes88@gmail.com
Requires-Python: >=3.11,<4.0
Classifier: License :: OSI Approved :: MIT License
Classifier: Programming Language :: Python :: 3
Classifier: Programming Language :: Python :: 3.11
Classifier: Programming Language :: Python :: 3.12
Requires-Dist: aiofiles (>=23.2.1,<24.0.0)
Requires-Dist: aiolimiter (>=1.1.0,<2.0.0)
Requires-Dist: asyncclick (>=8.1.7.2,<9.0.0.0)
Requires-Dist: bibtexparser (>=1.4.1,<2.0.0)
Requires-Dist: httpx (>=0.27.0,<0.28.0)
Requires-Dist: jupyter (>=1.0.0,<2.0.0)
Requires-Dist: tzdata (>=2024.1,<2025.0)
